hubble_github/__init__.py
hubble_github/__main__.py
hubble_github/display.py
hubble_github/search.py
hubble_github-0.0.5.dist-info/DESCRIPTION.rst
hubble_github-0.0.5.dist-info/METADATA
hubble_github-0.0.5.dist-info/RECORD
hubble_github-0.0.5.dist-info/WHEEL
hubble_github-0.0.5.dist-info/entry_points.txt
hubble_github-0.0.5.dist-info/metadata.json
hubble_github-0.0.5.dist-info/top_level.txt
